install_torch.py
install_torch-1.0.dist-info/entry_points.txt
install_torch-1.0.dist-info/LICENSE
install_torch-1.0.dist-info/METADATA
install_torch-1.0.dist-info/WHEEL
install_torch-1.0.dist-info/RECORD
