Metadata-Version: 2.1
Name: install-torch
Version: 1.0
Summary: This script can be used to automatically install torch and CUDA.
License: MIT
Author: Mikołaj Badyl
Author-email: mbadyl@outlook.com
Requires-Python: >=3.7
Classifier: License :: OSI Approved :: MIT License
Classifier: Programming Language :: Python :: 3
Classifier: Programming Language :: Python :: 3.7
Classifier: Programming Language :: Python :: 3.8
Classifier: Programming Language :: Python :: 3.9
Classifier: Programming Language :: Python :: 3.10
Classifier: Programming Language :: Python :: 3.11
Requires-Dist: beautifulsoup4 (>=4.12.2,<5.0.0)
Requires-Dist: requests (==2.26.0)
Requires-Dist: requests-html (>=0.10.0,<0.11.0)
Requires-Dist: rich (>=13.3.5,<14.0.0)
Requires-Dist: tqdm (>=4.65.0,<5.0.0)
Requires-Dist: wget (>=3.2,<4.0)
